[
    {
        "authors": "Lanouette, K., & Van Wart, S.J.",
        "date": "2026",
        "year": "2026",
        "title": "Digging Deeper into Schoolyards and Data: An elementary ecology unit to lift up children’s local knowledge",
        "venue": "Science and Children",
        "volume": 63,
        "issue": "1",
        "pages": "53-64",
        "type": "journal",
        "doi": "https://doi.org/10.1080/00368148.2025.2586296"
    },
    {
        "authors": "Lanouette, K., Van Wart, S.J., & Parikh, T.S.",
        "date": "2025",
        "year": "2025",
        "title": "Participatory Digital Mapping, Dynamic Data and Children's Emergent Science Argumentation about Local Socio-Ecological Systems",
        "venue": "Journal of Science Education and Technology",
        "volume": 34,
        "pages": "215-235",
        "type": "journal",
        "doi": "https://doi.org/10.1007/s10956-024-10152-6"
    },
    {
        "authors": "Chávez, V. & Van Wart, S.J.",
        "date": "2023, June 10-15",
        "year": "2023",
        "title": "“Accessibility is important to everybody”: Unpacking Students’ Understanding about Accessibility",
        "venue": "International Society of the Learning Sciences (ISLS)",
        "location": "Montréal, CA",
        "type": "conference",
        "url": "https://repository.isls.org/handle/1/9951"
    },
    {
        "title": "Scripts and counterscripts in community-based data science: Participatory digital mapping and the pursuit of a third space",
        "authors": "Van Wart, S.J., Lanouette, K., Parikh, T.S.",
        "date": "2020",
        "year": "2020",
        "type": "journal",
        "venue": "Journal of the Learning Sciences",
        "doi": "https://doi.org/10.1080/10508406.2019.1693378"
    },
    {
        "title": "Moving Between Experience, Data and Explanation: The Role of Participatory GIS Maps in Elementary Science Sensemaking",
        "authors": "Lanouette, K., Van Wart, S.J.",
        "date": "2019",
        "year": "2019",
        "type": "conference",
        "venue": "Computer Supported Collaborative Learning (CSCL)",
        "url": "https://ris.utwente.nl/ws/portalfiles/portal/129957345/CSCL_2019_Volume_2.pdf#page=39",
        "pages": "pp. 553–556",
        "location": "Lyon, FR"
    },
    {
        "title": "Supporting elementary students' learning about ecological systems through data modeling and interactive mapping in local contexts",
        "authors": "Lanouette, K., Van Wart, S.J., & Parikh, T.S.",
        "date": "2016",
        "year": "2016",
        "type": "conference",
        "venue": "International Conference of the Learning Sciences (ICLS)",
        "pages": "Vol. 1, pp. 570-577",
        "location": "Singapore"
    },
    {
        "title": "Apps for social justice: Motivating computer science learning with design and real-world problem solving",
        "authors": "Van Wart, S.J., Vakil, S., & Parikh, T.S.",
        "date": "2014",
        "year": "2014",
        "type": "conference",
        "venue": "Innovation & Technology in Computer Science Education (ITiCSE)",
        "pages": "123-128",
        "location": "Uppsala, SE",
        "doi": "https://dl.acm.org/doi/10.1145/2591708.2591751"
    },
    {
        "title": "Local Ground: A Paper-Based Toolkit for Documenting Local Geo-spatial Knowledge",
        "authors": "Van Wart, S.J., Tsai, K.J., & Parikh, T.S.",
        "date": "2010",
        "year": "2010",
        "type": "conference",
        "venue": "ACM Symposium on Computing for Development (ACMDEV)",
        "pages": "123-128",
        "location": "Egham, UK",
        "doi": "https://doi.org/10.1145/1926180.1926194"
    },
    {
        "title": "Participatory Digital Mapping, Dynamic Data, and Children's Science Argumentation: Possibilities in Elementary Science Ecology Studies",
        "authors": "Lanouette, K., Van Wart, S.J., & Parikh, T.S",
        "date": "2024",
        "year": "2024",
        "type": "workshop",
        "venue": "Annual Meeting of the American Educational Research Association (AERA)",
        "location": "Philadelphia, PA"
    },
    {
        "title": "Developing Artificial Intelligence Literacy by Examining the Politics of Internet Platforms",
        "chairs": "Zheng et al. (chairs)",
        "symposium_title": "Artificial Intelligence in Education: Potentials and Challenges in Ethics, Data Privacy, and Pedagogy",
        "authors": "Van Wart, S.J., Vakil, S., & araujo melo, n.",
        "date": "2023",
        "year": "2023",
        "type": "symposium",
        "venue": "American Educational Research Association (AERA)",
        "location": "Chicago, IL"
    },
    {
        "title": "“Google got yo' life”: Opening Portals for Ethical Sensemaking with Relational Design",
        "authors": "araujo melo, n., Reith, A., Nober, B., Van Wart, S.J., & Vakil, S.",
        "date": "2022",
        "year": "2022",
        "type": "workshop",
        "venue": "Annual Meeting of the American Educational Research Association (AERA)",
        "location": "San Diego, CA"
    },
    {
        "title": "Bringing Politics and Power into Computing Education: Young People’s Race, Power, and Technology Project",
        "authors": "(in alphabetical order) araujo melo, n., Bhadriraju, S., Elliot, S., Logan, C., Mehta, B., Reith, A., Vakil, S., Van Wart, S., Voelkel, G., Watson Jr., C., Wetoska, N., & Williams, T.",
        "date": "7-30 July 2021",
        "year": "2021",
        "type": "workshop",
        "venue": "Connected Learning Summit",
        "location": "Online"
    },
    {
        "title": "Data Literacies and Social Justice: Exploring Critical Data Literacies through Sociocultural Perspectives",
        "authors": "Irgens, G. A., Simon, K., Wise, A., Philip, T., Olivares, M. C., Van Wart, S.J., …  & Kahn, J.",
        "date": "21-23 July, 2020",
        "year": "2020",
        "type": "workshop",
        "venue": "International Conference of the Learning Sciences",
        "location": "Nashville, TN",
        "pages": "Vol. 1, pp. 406-413",
        "doi": "https://doi.dx.org/10.22318/icls2020.406"
    },
    {
        "title": "Data Literacy for Social Justice",
        "authors": "Matuk, C., Yoon, S., Polman, J., Barton, J., Bulalacao, N. M., Cafaro, F.,  & … Woods, P.",
        "date": "21-23 July, 2020",
        "year": "2020",
        "type": "workshop",
        "venue": "International Conference of the Learning Sciences",
        "location": "Nashville, TN",
        "pages": "Vol. 1, pp. 343–349",
        "doi": "https://doi.dx.org/10.22318/icls2020.343"
    },
    {
        "title": "Local Ground: Supporting local, data-driven inquiry with youth",
        "authors": "Van Wart, S.J., Lanouette, K., & Parikh, T.S.",
        "date": "2016",
        "year": "2016",
        "type": "workshop",
        "venue": "Annual Meeting of the American Educational Research Association (AERA)",
        "location": " Washington, D.C."
    },
    {
        "title": "Computer science meets social studies: Embedding CS in the study of locally grounded civic issues",
        "authors": "Van Wart, S.J.",
        "date": "2015",
        "year": "2015",
        "type": "workshop",
        "venue": "International Conference on International Computing Education Research (ICER)",
        "location": "Omaha, NE",
        "pages": "281-282",
        "doi": "https://dl.acm.org/doi/10.1145/2787622.2787751"
    },
    {
        "title": "Local Ground: A Toolkit Supporting Metarepresentational Competence in Data Science.",
        "authors": "Van Wart, S.J. & Parikh, T.S.",
        "date": "2014",
        "year": "2014",
        "type": "poster",
        "venue": "International Conference of the Learning Sciences (ICLS)",
        "location": "Boulder, CO",
        "pages": "1589-1590"
    },
    {
        "title": "Increasing Youth and Community Agency in GIS",
        "authors": "Van Wart, S.J. & Parikh, T.S.",
        "date": "2013",
        "year": "2013",
        "type": "workshop",
        "venue": "Geographic Human-Computer Interaction (GeoHCI) Workshop at SIGCHI",
        "location": "Paris, FR",
        "pages": "1-3",
        "url": "https://www-users.cs.umn.edu/~bhecht/geohci2013ps/GeoHCI2013_Proceedings.pdf"
    },
    {
        "authors": "Soep, E., Lee, C., Van Wart, S.J., Parikh, T.S.",
        "title": "Code for What?",
        "editors": "Jenkins, H., Peters-Lazaro, G., & Shresthova S.",
        "date": "2020",
        "year": "2020",
        "type": "book chapter",
        "venue": "Popular Culture and the Civic Imagination: Case Studies of Creative Social Change",
        "published": "NYU Press",
        "pages": "89-99",
        "url": "https://nyupress.org/9781479869503/popular-culture-and-the-civic-imagination/"
    },
    {
        "title": "Cal-Adapt: Bringing global climate change data to a local application",
        "authors": "Koy, K., Van Wart, S.J., Galey, B., O'Connor, M., & Kelly, M.",
        "date": "March 2011",
        "year": "2011",
        "type": "magazine",
        "venue": "PE&RS, Photogrammetric Engineering & Remote Sensing",
        "volume": "77",
        "issue": "6",
        "pages": "546-550"
    },
    {
        "title": "In search of a \"fair explanation\": Helping young people to consider the possibilities, limitations, and risks of computer- and data-mediated systems",
        "authors": "Van Wart, S.J.",
        "date": "2019",
        "year": "2019",
        "type": "dissertation",
        "venue": "Doctoral Dissertation",
        "url": "https://escholarship.org/content/qt58x6p9km/qt58x6p9km.pdf"
    }
]
